estim8/__init__.py
estim8/datatypes.py
estim8/error_models.py
estim8/estimator.py
estim8/generalized_islands.py
estim8/models.py
estim8/objective.py
estim8/optimizers.py
estim8/profile.py
estim8/py.typed
estim8/utils.py
estim8/visualization.py
estim8/workers.py
estim8-0.1.1.dist-info/METADATA
estim8-0.1.1.dist-info/WHEEL
estim8-0.1.1.dist-info/top_level.txt
estim8-0.1.1.dist-info/RECORD
