Metadata-Version: 2.1
Name: estim8
Version: 0.1.1
Summary: A parameter estimation tool for DAE models implemented compliant to the Functional Mockup Interface
Author-email: Tobias Latour <t.latour@fz-juelich.de>, Daniel Strohmeier <d.strohmeier@fz-juelich.de>
License: AGPLv3
Project-URL: GitHub, https://github.com/JuBiotech/estim8
Keywords: Biorpocessmodeling,Parameter estimation,Functional Mockup Interface
Classifier: Programming Language :: Python :: 3
Classifier: Operating System :: OS Independent
Classifier: License :: OSI Approved :: GNU Affero General Public License v3
Classifier: Intended Audience :: Science/Research
Requires-Python: <3.13,>=3.10.0
Requires-Dist: numpy<2,>=1.26.0
Requires-Dist: fmpy
Requires-Dist: scikit-optimize
Requires-Dist: scikit-learn
Requires-Dist: matplotlib
Requires-Dist: seaborn
Requires-Dist: pandas
Requires-Dist: pytensor-federated
Requires-Dist: pytensor
Requires-Dist: grpclib
Requires-Dist: openpyxl
